odoo9_addon_customer_activity_statement-9.0.1.0.0-py2.7-nspkg.pth
odoo9_addon_customer_activity_statement-9.0.1.0.0.dist-info/DESCRIPTION.rst
odoo9_addon_customer_activity_statement-9.0.1.0.0.dist-info/METADATA
odoo9_addon_customer_activity_statement-9.0.1.0.0.dist-info/RECORD
odoo9_addon_customer_activity_statement-9.0.1.0.0.dist-info/WHEEL
odoo9_addon_customer_activity_statement-9.0.1.0.0.dist-info/metadata.json
odoo9_addon_customer_activity_statement-9.0.1.0.0.dist-info/namespace_packages.txt
odoo9_addon_customer_activity_statement-9.0.1.0.0.dist-info/top_level.txt
odoo_addons/customer_activity_statement/README.rst
odoo_addons/customer_activity_statement/__init__.py
odoo_addons/customer_activity_statement/__openerp__.py
odoo_addons/customer_activity_statement/report/__init__.py
odoo_addons/customer_activity_statement/report/customer_activity_statement.py
odoo_addons/customer_activity_statement/static/description/Activity_Statement.png
odoo_addons/customer_activity_statement/static/description/icon.png
odoo_addons/customer_activity_statement/static/description/index.html
odoo_addons/customer_activity_statement/tests/__init__.py
odoo_addons/customer_activity_statement/tests/test_customer_activity_statement.py
odoo_addons/customer_activity_statement/views/statement.xml
odoo_addons/customer_activity_statement/wizard/__init__.py
odoo_addons/customer_activity_statement/wizard/customer_activity_statement_wizard.py
odoo_addons/customer_activity_statement/wizard/customer_activity_statement_wizard.xml
